{
    "persona": "Persona: Olivia\n\nBackground:\nOlivia is a dynamic and successful business executive who has spent the past three decades building an impressive career. As the CEO of a thriving tech startup, she has navigated the challenges of the corporate world with unwavering determination and strategic vision. Despite her demanding professional responsibilities, Olivia remains committed to maintaining a balanced and fulfilling personal life.\n\nDemographics:\nAge: 59\nGender: Female\nEducation: Master's Degree in Business Administration\nProfession: CEO of a Tech Startup\nIncome: $185,000\n\nFinancial Situation:\nOlivia's impressive income as the CEO of a successful tech company provides her with a comfortable and stable financial foundation. She is a savvy investor, carefully managing her assets to ensure long-term financial security. While Olivia enjoys the occasional splurge, she is also mindful of responsible financial planning, setting aside funds for retirement and philanthropic endeavors.\n\nShopping Habits:\nOlivia's shopping habits reflect her sophisticated and discerning taste. She is selective in her purchases, focusing on high-quality, timeless pieces that complement her personal style. She enjoys browsing upscale boutiques and designer showrooms, but also appreciates the value of carefully researching and comparing options to ensure she is making informed decisions.\n\nPersonal Style:\nOlivia's personal style is a seamless blend of classic elegance and modern sophistication. She curates a wardrobe of tailored, sophisticated pieces, such as well-fitted blazers, sleek pants, and timeless dresses. Her accessory choices often make a statement, with statement jewelry, designer handbags, and carefully chosen footwear.\n\nPersonal Life:\nDespite her demanding career, Olivia places a strong emphasis on maintaining a healthy work-life balance. She enjoys spending quality time with her close-knit circle of friends and family, engaging in activities such as hosting dinner parties, attending cultural events, and traveling to explore new destinations. Olivia is also an active supporter of various philanthropic causes, dedicating both her time and resources to making a positive impact in her community.",
    "intent": "buy travel size toiletry containers.",
    "age": 59,
    "age_group": "55-64",
    "gender": "female",
    "income": [
        94001,
        1000000
    ],
    "income_group": "94001-1000000"
}