{
    "persona": "Persona: Amelia\n\nBackground:\nAmelia is a resilient and compassionate 64-year-old woman who has faced a lifetime of challenges. After retiring from a career in social work, Amelia found herself in a financial predicament, relying on a limited income and community resources to get by. Despite these difficulties, she remains dedicated to supporting her local community and using her wealth of experience to make a difference in the lives of others.\n\nDemographics:\nAge: 64\nGender: Female\nEducation: Bachelor's Degree in Social Work\nProfession: Retired Social Worker\nIncome: $18,000 (from pension and government assistance)\n\nFinancial Situation:\nAmelia's fixed income from her pension and government assistance programs is just enough to cover her basic living expenses, with little left over for discretionary spending. She carefully budgets her funds, relying on community resources, such as food banks and subsidized housing, to make ends meet. Amelia's financial situation requires constant vigilance, but she remains determined to maintain her independence and continue contributing to her community.\n\nShopping Habits:\nAmelia approaches shopping with a pragmatic and resourceful mindset. She frequents thrift stores, secondhand shops, and discount retailers in search of affordable, high-quality items that will meet her needs. Amelia is skilled at finding creative solutions, whether it's repurposing household items or taking advantage of sales and coupons. She values practicality and functionality over trends, and she takes pride in her ability to stretch her limited budget to provide for herself and, when possible, support others in need.\n\nPersonal Life:\nDespite her financial constraints, Amelia remains actively involved in her local community. She volunteers at a nearby senior center, providing emotional support and practical assistance to her peers. Amelia also serves on the board of a local non-profit organization, using her expertise in social work to advocate for the needs of marginalized populations. Her compassion and resilience inspire those around her, and Amelia finds great fulfillment in making a positive impact on the lives of others.\n\nPersonal Style:\nAmelia's personal style reflects her practical and community-oriented approach to life. Her wardrobe consists of comfortable, durable clothing, often acquired from secondhand sources or gifted by friends and family members. She values functionality and versatility, opting for items that can be easily mixed and matched to create a variety of outfits. Amelia's style is modest and unassuming, but it also conveys a sense of dignity and self-respect, as she navigates the challenges of her later years with grace and determination.",
    "intent": "buy a small surface grinder.",
    "age": 64,
    "age_group": "55-64",
    "gender": "female",
    "income": [
        0,
        30000
    ],
    "income_group": "0-30000"
}