{
    "persona": "Persona: Nicole\n\nBackground:\nNicole is a driven and ambitious marketing executive who has built a successful career in the fast-paced world of digital advertising. With a keen understanding of consumer behavior and a knack for developing innovative campaigns, she has risen through the ranks to become the Vice President of Marketing at a leading tech company.\n\nDemographics:\nAge: 36\nGender: Female\nEducation: Master's Degree in Marketing\nProfession: Vice President of Marketing\nIncome: $125,000\n\nFinancial Situation:\nAs a high-level executive, Nicole enjoys a comfortable financial standing. She has a robust investment portfolio and a substantial savings account that provide her with a sense of financial security. While she is not driven by material possessions, Nicole is willing to invest in quality products and services that enhance her professional and personal life.\n\nShopping Habits:\nNicole's shopping habits reflect her pragmatic and strategic mindset. She tends to invest in timeless, high-quality items that exude sophistication and professionalism. When making purchases, Nicole prioritizes functionality, versatility, and practicality, often opting for classic silhouettes and neutral color palettes that can seamlessly integrate into her wardrobe. She is selective in her spending, focusing on key pieces that will serve her well in both her professional and personal life.\n\nProfessional Life:\nAs the Vice President of Marketing, Nicole is responsible for overseeing the development and execution of strategic marketing campaigns that drive brand awareness and customer engagement. She works closely with her team of marketing professionals to analyze market trends, identify target audiences, and develop innovative content strategies that resonate with consumers. Nicole is known for her analytical problem-solving skills, her ability to think outside the box, and her knack for leading high-performing teams.\n\nPersonal Style:\nNicole's personal style is a reflection of her professional persona \u2013 polished, sophisticated, and effortlessly chic. She favors well-tailored blazers, sophisticated dresses, and sleek leather accessories that exude a sense of authority and confidence. While her wardrobe is primarily centered around workwear, Nicole also enjoys incorporating elegant, timeless pieces that can be easily transitioned from the office to social events. She values quality over quantity and invests in investment pieces that will stand the test of time.",
    "intent": "buy a high-quality smoke machine for outdoor Halloween decorations.",
    "age": 36,
    "age_group": "35-44",
    "gender": "female",
    "income": [
        94001,
        1000000
    ],
    "income_group": "94001-1000000"
}