{
    "persona": "Persona: Jessica\n\nBackground:\nJessica is a seasoned human resources professional with a passion for fostering positive workplace cultures. With over two decades of experience, she has developed a keen understanding of people management and organizational dynamics, enabling her to guide her company's workforce strategies.\n\nDemographics:\nAge: 52\nGender: Female\nEducation: Bachelor's Degree in Human Resources Management\nProfession: Human Resources Manager\nIncome: $68,000\n\nFinancial Situation:\nJessica's steady income and careful financial planning have allowed her to maintain a comfortable lifestyle. She prioritizes saving for retirement and emergency funds, while also allocating resources towards occasional travel and hobbies that bring her joy. Jessica values financial security and takes pride in her ability to manage her finances responsibly.\n\nShopping Habits:\nAs a busy professional, Jessica appreciates the convenience and efficiency of online shopping, but she also enjoys the tactile experience of in-store browsing. She seeks out quality, long-lasting products that align with her personal style and values. Jessica takes the time to research and compare options, ensuring she makes informed purchasing decisions.\n\nProfessional Life:\nIn her role as a human resources manager, Jessica is instrumental in shaping the employee experience at her organization. She is skilled at navigating complex workplace dynamics, resolving conflicts, and developing policies that promote inclusivity, well-being, and professional growth. Jessica's colleagues recognize her as a trusted advisor and a champion for positive organizational change.\n\nPersonal Style:\nJessica's personal style reflects her poise and professionalism. She favors tailored, versatile pieces that can seamlessly transition from the office to after-work events. Her wardrobe consists of well-fitting blazers, structured dresses, and high-quality accessories that convey a sense of polished sophistication. Jessica values comfort and practicality, but she is not afraid to incorporate stylish, statement-making elements into her outfits.\n\nIn her free time, Jessica enjoys engaging in activities that rejuvenate her mind and body, such as practicing yoga, reading literary fiction, and exploring local art exhibitions. She cherishes the opportunity to disconnect from work and focus on her personal growth and well-being.",
    "intent": "buy a men's necklace chain with a pendant.",
    "age": 52,
    "age_group": "45-54",
    "gender": "female",
    "income": [
        30001,
        94000
    ],
    "income_group": "30001-94000"
}